cascade/__init__.py
cascade/bridge.py
cascade/cli_main.py
cascade/demo.py
cascade/demo_sdk.py
cascade/genesis.py
cascade/identity.py
cascade/ipld.py
cascade/listen.py
cascade/observation.py
cascade/observe.py
cascade/proxy.py
cascade/py.typed
cascade/sdk.py
cascade/store.py
cascade/torch_hook.py
cascade/web3_pin.py
cascade/analysis/__init__.py
cascade/analysis/metrics.py
cascade/analysis/tracer.py
cascade/core/__init__.py
cascade/core/adapter.py
cascade/core/event.py
cascade/core/graph.py
cascade/core/provenance.py
cascade/core/web3_bridge.py
cascade/data/__init__.py
cascade/data/croissant.py
cascade/data/entities.py
cascade/data/hub.py
cascade/data/license.py
cascade/data/live.py
cascade/data/observer.py
cascade/data/pii.py
cascade/data/provenance.py
cascade/data/schema.py
cascade/diagnostics/__init__.py
cascade/diagnostics/bug_detector.py
cascade/diagnostics/code_tracer.py
cascade/diagnostics/demo.py
cascade/diagnostics/execution_monitor.py
cascade/diagnostics/report.py
cascade/export/__init__.py
cascade/export/tableau_export.py
cascade/forensics/__init__.py
cascade/forensics/analyzer.py
cascade/forensics/artifacts.py
cascade/forensics/fingerprints.py
cascade/hold/__init__.py
cascade/hold/primitives.py
cascade/hold/session.py
cascade/logging/__init__.py
cascade/logging/color_example.py
cascade/logging/integrate.py
cascade/logging/interpretive_logger.py
cascade/logging/kleene_logger.py
cascade/logging/log_manager.py
cascade/patches/__init__.py
cascade/patches/anthropic_patch.py
cascade/patches/huggingface_patch.py
cascade/patches/litellm_patch.py
cascade/patches/ollama_patch.py
cascade/patches/openai_patch.py
cascade/system/__init__.py
cascade/system/adapter.py
cascade/system/file_extractors.py
cascade/system/folder_processor.py
cascade/system/moe_analyzer.py
cascade/system/observer.py
cascade/system/omnidirectional_analyzer.py
cascade/system/repo_ingester.py
cascade/system/universal_extractor.py
cascade/viz/__init__.py
cascade/viz/tape.py
cascade_lattice-0.6.0.dist-info/METADATA
cascade_lattice-0.6.0.dist-info/WHEEL
cascade_lattice-0.6.0.dist-info/entry_points.txt
cascade_lattice-0.6.0.dist-info/licenses/LICENSE
cascade_lattice-0.6.0.dist-info/RECORD
