Metadata-Version: 2.4
Name: cascade-lattice
Version: 0.6.0
Summary: Universal AI provenance layer — cryptographic receipts for every call, HOLD inference halt protocol, and code diagnostics
Project-URL: Homepage, https://github.com/Yufok1/cascade-lattice
Project-URL: Documentation, https://github.com/Yufok1/cascade-lattice#readme
Project-URL: Repository, https://github.com/Yufok1/cascade-lattice
Project-URL: Issues, https://github.com/Yufok1/cascade-lattice/issues
Author: Jeff Towers
License-Expression: MIT
License-File: LICENSE
Keywords: ai,bug-detection,cryptographic,debugging,diagnostics,hold-protocol,llm,ml,monitoring,observability,provenance,receipts,static-analysis,tracing
Classifier: Development Status :: 4 - Beta
Classifier: Intended Audience :: Developers
Classifier: Intended Audience :: Science/Research
Classifier: License :: OSI Approved :: MIT License
Classifier: Programming Language :: Python :: 3
Classifier: Programming Language :: Python :: 3.8
Classifier: Programming Language :: Python :: 3.9
Classifier: Programming Language :: Python :: 3.10
Classifier: Programming Language :: Python :: 3.11
Classifier: Programming Language :: Python :: 3.12
Classifier: Topic :: Scientific/Engineering :: Artificial Intelligence
Classifier: Topic :: System :: Monitoring
Requires-Python: >=3.9
Requires-Dist: aiohttp>=3.8.0
Requires-Dist: dag-cbor>=0.3.0
Requires-Dist: multiformats>=0.3.0
Requires-Dist: numpy>=1.20.0
Requires-Dist: rich>=12.0.0
Provides-Extra: all
Requires-Dist: anthropic>=0.18.0; extra == 'all'
Requires-Dist: datasets>=2.14.0; extra == 'all'
Requires-Dist: huggingface-hub>=0.20.0; extra == 'all'
Requires-Dist: langchain>=0.1.0; extra == 'all'
Requires-Dist: litellm>=1.0.0; extra == 'all'
Requires-Dist: networkx>=2.6; extra == 'all'
Requires-Dist: ollama>=0.1.0; extra == 'all'
Requires-Dist: openai>=1.0.0; extra == 'all'
Requires-Dist: sentence-transformers>=2.2.0; extra == 'all'
Requires-Dist: transformers>=4.30.0; extra == 'all'
Provides-Extra: anthropic
Requires-Dist: anthropic>=0.18.0; extra == 'anthropic'
Provides-Extra: demo
Requires-Dist: box2d-py>=2.3.5; extra == 'demo'
Requires-Dist: gymnasium>=0.29.0; extra == 'demo'
Requires-Dist: pygame>=2.1.0; extra == 'demo'
Requires-Dist: rl-zoo3>=2.0.0; extra == 'demo'
Requires-Dist: stable-baselines3>=2.0.0; extra == 'demo'
Provides-Extra: dev
Requires-Dist: black>=23.0; extra == 'dev'
Requires-Dist: mypy>=1.0; extra == 'dev'
Requires-Dist: pytest-asyncio>=0.21.0; extra == 'dev'
Requires-Dist: pytest-cov>=4.0; extra == 'dev'
Requires-Dist: pytest>=7.0; extra == 'dev'
Requires-Dist: ruff>=0.1.0; extra == 'dev'
Provides-Extra: hold
Requires-Dist: numpy>=1.20.0; extra == 'hold'
Provides-Extra: huggingface
Requires-Dist: huggingface-hub>=0.20.0; extra == 'huggingface'
Requires-Dist: transformers>=4.30.0; extra == 'huggingface'
Provides-Extra: ipfs
Requires-Dist: ipfshttpclient>=0.8.0; extra == 'ipfs'
Provides-Extra: langchain
Requires-Dist: langchain>=0.1.0; extra == 'langchain'
Provides-Extra: litellm
Requires-Dist: litellm>=1.0.0; extra == 'litellm'
Provides-Extra: ollama
Requires-Dist: ollama>=0.1.0; extra == 'ollama'
Provides-Extra: openai
Requires-Dist: openai>=1.0.0; extra == 'openai'
